{
    "generated": "2026-07-24T14:47:55",
    "shift": "1st",
    "facility": "499",
    "associates": [
        {
            "name": "gloria.miranda",
            "lpns": 58,
            "units": 0,
            "first_scan": "06:01",
            "last_scan": "07:44"
        },
        {
            "name": "harley.fox",
            "lpns": 45,
            "units": 10,
            "first_scan": "06:00",
            "last_scan": "07:43"
        },
        {
            "name": "myintmyint.than",
            "lpns": 44,
            "units": 1,
            "first_scan": "06:01",
            "last_scan": "07:47"
        },
        {
            "name": "jordan.hill1",
            "lpns": 39,
            "units": 15,
            "first_scan": "06:01",
            "last_scan": "07:47"
        },
        {
            "name": "carmen.caldwell",
            "lpns": 37,
            "units": 7,
            "first_scan": "06:00",
            "last_scan": "07:47"
        },
        {
            "name": "manuel.astorga",
            "lpns": 36,
            "units": 13,
            "first_scan": "06:00",
            "last_scan": "07:47"
        },
        {
            "name": "silvia.ruiz",
            "lpns": 34,
            "units": 2,
            "first_scan": "06:00",
            "last_scan": "07:43"
        },
        {
            "name": "marina.martinez",
            "lpns": 25,
            "units": 121,
            "first_scan": "06:01",
            "last_scan": "07:47"
        },
        {
            "name": "cesar.ramos1",
            "lpns": 17,
            "units": 51,
            "first_scan": "06:15",
            "last_scan": "06:19"
        },
        {
            "name": "robert.moraga",
            "lpns": 13,
            "units": 39,
            "first_scan": "06:00",
            "last_scan": "06:02"
        },
        {
            "name": "cynthia.gomez",
            "lpns": 8,
            "units": 6,
            "first_scan": "06:01",
            "last_scan": "06:14"
        },
        {
            "name": "raymond.rodriguez1",
            "lpns": 8,
            "units": 48,
            "first_scan": "06:43",
            "last_scan": "07:03"
        },
        {
            "name": "alexis.delrio",
            "lpns": 7,
            "units": 42,
            "first_scan": "06:33",
            "last_scan": "07:06"
        },
        {
            "name": "berena.quiterio",
            "lpns": 5,
            "units": 132,
            "first_scan": "06:00",
            "last_scan": "07:46"
        },
        {
            "name": "consuelotatiana.lopez",
            "lpns": 3,
            "units": 2,
            "first_scan": "06:10",
            "last_scan": "07:47"
        },
        {
            "name": "cecilia.aguilar",
            "lpns": 2,
            "units": 2,
            "first_scan": "07:05",
            "last_scan": "07:06"
        },
        {
            "name": "dulce.zamora",
            "lpns": 2,
            "units": 128,
            "first_scan": "06:15",
            "last_scan": "07:01"
        },
        {
            "name": "manhedgeuser",
            "lpns": 2,
            "units": 0,
            "first_scan": "06:49",
            "last_scan": "06:49"
        },
        {
            "name": "ileana.sales",
            "lpns": 1,
            "units": 5,
            "first_scan": "06:05",
            "last_scan": "06:05"
        },
        {
            "name": "maria.rodriguez2",
            "lpns": 1,
            "units": 6,
            "first_scan": "06:04",
            "last_scan": "06:04"
        },
        {
            "name": "reisel.ross",
            "lpns": 1,
            "units": 18,
            "first_scan": "07:39",
            "last_scan": "07:39"
        },
        {
            "name": "verenice.lozanolozano",
            "lpns": 1,
            "units": 133,
            "first_scan": "06:53",
            "last_scan": "06:53"
        }
    ],
    "hourly": [
        {
            "hour": 6,
            "lpns": 290,
            "units": 578
        },
        {
            "hour": 7,
            "lpns": 99,
            "units": 203
        }
    ]
}