{
    "generated": "2026-07-24T01:46:31",
    "facility": "499",
    "summary": {
        "total": 23,
        "case1": 0,
        "case2": 0,
        "case3": 23,
        "red": 13
    },
    "case1": [],
    "case2": [],
    "case3": [
        {
            "olpn": "T000009051",
            "type": "M",
            "units": 1,
            "case": 3,
            "location": "D1-PW-11",
            "loc_type": "PACKING",
            "created": "15:04",
            "timer_min": 118,
            "severity": "red"
        },
        {
            "olpn": "T000009627",
            "type": "M",
            "units": 2,
            "case": 3,
            "location": "D1-PW-01",
            "loc_type": "PACKING",
            "created": "16:49",
            "timer_min": 116,
            "severity": "red"
        },
        {
            "olpn": "T000009155",
            "type": "M",
            "units": 19,
            "case": 3,
            "location": "D1-PW-01",
            "loc_type": "PACKING",
            "created": "16:47",
            "timer_min": 115,
            "severity": "red"
        },
        {
            "olpn": "T000008569",
            "type": "S",
            "units": 1,
            "case": 3,
            "location": "D1-SN-01",
            "loc_type": "PACKING",
            "created": "15:19",
            "timer_min": 98,
            "severity": "red"
        },
        {
            "olpn": "T000009454",
            "type": "M",
            "units": 18,
            "case": 3,
            "location": "D1-SN-01",
            "loc_type": "PACKING",
            "created": "14:36",
            "timer_min": 97,
            "severity": "red"
        },
        {
            "olpn": "T000008798",
            "type": "S",
            "units": 1,
            "case": 3,
            "location": "D1-SN-01",
            "loc_type": "PACKING",
            "created": "16:32",
            "timer_min": 94,
            "severity": "red"
        },
        {
            "olpn": "T000008339",
            "type": "M",
            "units": 39,
            "case": 3,
            "location": "D1-PW-01",
            "loc_type": "PACKING",
            "created": "17:03",
            "timer_min": 83,
            "severity": "red"
        },
        {
            "olpn": "T000009327",
            "type": "M",
            "units": 3,
            "case": 3,
            "location": "D1-PW-01",
            "loc_type": "PACKING",
            "created": "17:18",
            "timer_min": 83,
            "severity": "red"
        },
        {
            "olpn": "T000009708",
            "type": "M",
            "units": 3,
            "case": 3,
            "location": "D1-PW-01",
            "loc_type": "PACKING",
            "created": "17:21",
            "timer_min": 83,
            "severity": "red"
        },
        {
            "olpn": "T000008980",
            "type": "S",
            "units": 1,
            "case": 3,
            "location": "D1-SN-01",
            "loc_type": "PACKING",
            "created": "16:47",
            "timer_min": 79,
            "severity": "red"
        },
        {
            "olpn": "T000008354",
            "type": "S",
            "units": 1,
            "case": 3,
            "location": "D1-SN-01",
            "loc_type": "PACKING",
            "created": "13:22",
            "timer_min": 78,
            "severity": "red"
        },
        {
            "olpn": "T000009718",
            "type": "M",
            "units": 16,
            "case": 3,
            "location": "D1-PW-01",
            "loc_type": "PACKING",
            "created": "16:56",
            "timer_min": 67,
            "severity": "red"
        },
        {
            "olpn": "T000008739",
            "type": "M",
            "units": 29,
            "case": 3,
            "location": "D1-SN-01",
            "loc_type": "PACKING",
            "created": "16:53",
            "timer_min": 65,
            "severity": "red"
        },
        {
            "olpn": "T000008255",
            "type": "S",
            "units": 2,
            "case": 3,
            "location": "D1-SN-01",
            "loc_type": "PACKING",
            "created": "17:46",
            "timer_min": 57,
            "severity": "yellow"
        },
        {
            "olpn": "T000008518",
            "type": "S",
            "units": 3,
            "case": 3,
            "location": "D1-SN-01",
            "loc_type": "PACKING",
            "created": "17:51",
            "timer_min": 53,
            "severity": "yellow"
        },
        {
            "olpn": "T000008476",
            "type": "M",
            "units": 43,
            "case": 3,
            "location": "D1-PW-01",
            "loc_type": "PACKING",
            "created": "16:53",
            "timer_min": 37,
            "severity": "yellow"
        },
        {
            "olpn": "T000009579",
            "type": "S",
            "units": 1,
            "case": 3,
            "location": "D1-SN-01",
            "loc_type": "PACKING",
            "created": "18:11",
            "timer_min": 35,
            "severity": "yellow"
        },
        {
            "olpn": "T000010083",
            "type": "M",
            "units": 1,
            "case": 3,
            "location": "D1-PW-10",
            "loc_type": "PACKING",
            "created": "14:58",
            "timer_min": 34,
            "severity": "yellow"
        },
        {
            "olpn": "T000008332",
            "type": "M",
            "units": 36,
            "case": 3,
            "location": "D1-PW-11",
            "loc_type": "PACKING",
            "created": "15:22",
            "timer_min": 33,
            "severity": "yellow"
        },
        {
            "olpn": "T000008645",
            "type": "S",
            "units": 24,
            "case": 3,
            "location": "D1-SN-01",
            "loc_type": "PACKING",
            "created": "17:32",
            "timer_min": 32,
            "severity": "yellow"
        },
        {
            "olpn": "T000009313",
            "type": "S",
            "units": 1,
            "case": 3,
            "location": "D1-SN-01",
            "loc_type": "PACKING",
            "created": "15:48",
            "timer_min": 32,
            "severity": "yellow"
        },
        {
            "olpn": "T000010188",
            "type": "S",
            "units": 6,
            "case": 3,
            "location": "D1-SN-01",
            "loc_type": "PACKING",
            "created": "17:25",
            "timer_min": 32,
            "severity": "yellow"
        },
        {
            "olpn": "T000010143",
            "type": "S",
            "units": 11,
            "case": 3,
            "location": "D1-SN-01",
            "loc_type": "PACKING",
            "created": "17:25",
            "timer_min": 31,
            "severity": "yellow"
        }
    ],
    "putwalls": [
        {
            "pw": "PW1",
            "mawm_prefix": "S1-PW-010",
            "olpn_count": 42,
            "dz1": "D1-PW-01",
            "dz2": "D1-PW-09",
            "active_dz": "D1-SN-01",
            "dz1_totes": 7,
            "dz2_totes": 0
        },
        {
            "pw": "PW2",
            "mawm_prefix": "S1-PW-020",
            "olpn_count": 15,
            "dz1": "D1-PW-02",
            "dz2": "D1-PW-10",
            "active_dz": "D1-SN-01",
            "dz1_totes": 0,
            "dz2_totes": 1
        },
        {
            "pw": "PW3",
            "mawm_prefix": "S1-PW-030",
            "olpn_count": 22,
            "dz1": "D1-PW-03",
            "dz2": "D1-PW-11",
            "active_dz": "D1-PW-11",
            "dz1_totes": 0,
            "dz2_totes": 2
        },
        {
            "pw": "PW4",
            "mawm_prefix": "S1-PW-040",
            "olpn_count": 0,
            "dz1": "D1-PW-04",
            "dz2": "D1-PW-12",
            "active_dz": null,
            "dz1_totes": 0,
            "dz2_totes": 0
        },
        {
            "pw": "PW5",
            "mawm_prefix": "S1-PW-050",
            "olpn_count": 0,
            "dz1": "D1-PW-05",
            "dz2": "D1-PW-13",
            "active_dz": null,
            "dz1_totes": 0,
            "dz2_totes": 0
        },
        {
            "pw": "PW6",
            "mawm_prefix": "S1-PW-060",
            "olpn_count": 0,
            "dz1": "D1-PW-06",
            "dz2": "D1-PW-14",
            "active_dz": null,
            "dz1_totes": 0,
            "dz2_totes": 0
        },
        {
            "pw": "PW7",
            "mawm_prefix": "S1-PW-070",
            "olpn_count": 0,
            "dz1": "D1-PW-07",
            "dz2": "D1-PW-15",
            "active_dz": null,
            "dz1_totes": 0,
            "dz2_totes": 0
        },
        {
            "pw": "PW8",
            "mawm_prefix": "S1-PW-080",
            "olpn_count": 0,
            "dz1": "D1-PW-08",
            "dz2": "D1-PW-16",
            "active_dz": null,
            "dz1_totes": 0,
            "dz2_totes": 0
        },
        {
            "pw": "H1",
            "mawm_prefix": "H1-PW-01",
            "olpn_count": 3,
            "dz1": "D1-HP-01",
            "dz2": null,
            "active_dz": null,
            "dz1_totes": 0,
            "dz2_totes": 0
        }
    ]
}