{
    "generated": "2026-07-22T06:08:43",
    "facility": "499",
    "summary": {
        "total": 32,
        "case1": 0,
        "case2": 0,
        "case3": 32,
        "red": 12
    },
    "case1": [],
    "case2": [],
    "case3": [
        {
            "olpn": "T000008518",
            "type": "S",
            "units": 46,
            "case": 3,
            "location": "D1-SN-01",
            "loc_type": "PACKING",
            "created": "07:28",
            "timer_min": 2260,
            "severity": "red"
        },
        {
            "olpn": "T000009747",
            "type": "S",
            "units": 51,
            "case": 3,
            "location": "D1-SN-01",
            "loc_type": "PACKING",
            "created": "06:44",
            "timer_min": 2212,
            "severity": "red"
        },
        {
            "olpn": "T000010246",
            "type": "S",
            "units": 6,
            "case": 3,
            "location": "D1-SN-01",
            "loc_type": "PACKING",
            "created": "10:03",
            "timer_min": 2168,
            "severity": "red"
        },
        {
            "olpn": "T000009221",
            "type": "S",
            "units": 27,
            "case": 3,
            "location": "D1-SN-01",
            "loc_type": "PACKING",
            "created": "07:47",
            "timer_min": 2103,
            "severity": "red"
        },
        {
            "olpn": "T000010131",
            "type": "S",
            "units": 45,
            "case": 3,
            "location": "D1-SN-01",
            "loc_type": "PACKING",
            "created": "07:43",
            "timer_min": 2086,
            "severity": "red"
        },
        {
            "olpn": "T000009929",
            "type": "S",
            "units": 18,
            "case": 3,
            "location": "D1-SN-01",
            "loc_type": "PACKING",
            "created": "11:09",
            "timer_min": 2076,
            "severity": "red"
        },
        {
            "olpn": "T000008356",
            "type": "S",
            "units": 38,
            "case": 3,
            "location": "D1-SN-01",
            "loc_type": "PACKING",
            "created": "15:36",
            "timer_min": 1530,
            "severity": "red"
        },
        {
            "olpn": "T000008050",
            "type": "S",
            "units": 16,
            "case": 3,
            "location": "D1-SN-01",
            "loc_type": "PACKING",
            "created": "10:01",
            "timer_min": 761,
            "severity": "red"
        },
        {
            "olpn": "T000010114",
            "type": "S",
            "units": 17,
            "case": 3,
            "location": "D1-SN-01",
            "loc_type": "PACKING",
            "created": "15:24",
            "timer_min": 429,
            "severity": "red"
        },
        {
            "olpn": "T000008788",
            "type": "S",
            "units": 6,
            "case": 3,
            "location": "D1-SN-01",
            "loc_type": "PACKING",
            "created": "16:33",
            "timer_min": 377,
            "severity": "red"
        },
        {
            "olpn": "T000009215",
            "type": "M",
            "units": 8,
            "case": 3,
            "location": "D1-PW-10",
            "loc_type": "PACKING",
            "created": "22:18",
            "timer_min": 47,
            "severity": "red"
        },
        {
            "olpn": "T000008330",
            "type": "M",
            "units": 24,
            "case": 3,
            "location": "D1-PW-10",
            "loc_type": "PACKING",
            "created": "22:22",
            "timer_min": 41,
            "severity": "red"
        },
        {
            "olpn": "T000010102",
            "type": "M",
            "units": 31,
            "case": 3,
            "location": "D1-PW-10",
            "loc_type": "PACKING",
            "created": "22:34",
            "timer_min": 27,
            "severity": "yellow"
        },
        {
            "olpn": "T000008725",
            "type": "M",
            "units": 3,
            "case": 3,
            "location": "D1-PW-10",
            "loc_type": "PACKING",
            "created": "22:27",
            "timer_min": 26,
            "severity": "yellow"
        },
        {
            "olpn": "T000010293",
            "type": "S",
            "units": 1,
            "case": 3,
            "location": "D1-SN-01",
            "loc_type": "PACKING",
            "created": "22:43",
            "timer_min": 23,
            "severity": "yellow"
        },
        {
            "olpn": "T000007984",
            "type": "S",
            "units": 1,
            "case": 3,
            "location": "D1-SN-01",
            "loc_type": "PACKING",
            "created": "22:43",
            "timer_min": 23,
            "severity": "yellow"
        },
        {
            "olpn": "T000010359",
            "type": "M",
            "units": 25,
            "case": 3,
            "location": "D1-PW-10",
            "loc_type": "PACKING",
            "created": "22:18",
            "timer_min": 14,
            "severity": "green"
        },
        {
            "olpn": "T000008842",
            "type": "M",
            "units": 23,
            "case": 3,
            "location": "D1-PW-10",
            "loc_type": "PACKING",
            "created": "22:27",
            "timer_min": 14,
            "severity": "green"
        },
        {
            "olpn": "T000010273",
            "type": "M",
            "units": 29,
            "case": 3,
            "location": "D1-PW-10",
            "loc_type": "PACKING",
            "created": "22:35",
            "timer_min": 14,
            "severity": "green"
        },
        {
            "olpn": "T000009118",
            "type": "M",
            "units": 26,
            "case": 3,
            "location": "D1-PW-10",
            "loc_type": "PACKING",
            "created": "22:35",
            "timer_min": 14,
            "severity": "green"
        },
        {
            "olpn": "T000009538",
            "type": "M",
            "units": 17,
            "case": 3,
            "location": "D1-PW-10",
            "loc_type": "PACKING",
            "created": "22:49",
            "timer_min": 14,
            "severity": "green"
        },
        {
            "olpn": "T000008401",
            "type": "M",
            "units": 1,
            "case": 3,
            "location": "D1-PW-10",
            "loc_type": "PACKING",
            "created": "22:53",
            "timer_min": 14,
            "severity": "green"
        },
        {
            "olpn": "T000009230",
            "type": "M",
            "units": 9,
            "case": 3,
            "location": "D1-PW-10",
            "loc_type": "PACKING",
            "created": "22:49",
            "timer_min": 12,
            "severity": "green"
        },
        {
            "olpn": "T000010172",
            "type": "M",
            "units": 9,
            "case": 3,
            "location": "D1-PW-10",
            "loc_type": "PACKING",
            "created": "22:53",
            "timer_min": 12,
            "severity": "green"
        },
        {
            "olpn": "T000008873",
            "type": "M",
            "units": 11,
            "case": 3,
            "location": "D1-PW-10",
            "loc_type": "PACKING",
            "created": "22:54",
            "timer_min": 12,
            "severity": "green"
        },
        {
            "olpn": "T000009020",
            "type": "S",
            "units": 7,
            "case": 3,
            "location": "D1-SN-01",
            "loc_type": "PACKING",
            "created": "22:58",
            "timer_min": 8,
            "severity": "green"
        },
        {
            "olpn": "T000009349",
            "type": "S",
            "units": 1,
            "case": 3,
            "location": "D1-SN-01",
            "loc_type": "PACKING",
            "created": "22:27",
            "timer_min": 7,
            "severity": "green"
        },
        {
            "olpn": "T000009820",
            "type": "S",
            "units": 16,
            "case": 3,
            "location": "D1-SN-01",
            "loc_type": "PACKING",
            "created": "22:35",
            "timer_min": 7,
            "severity": "green"
        },
        {
            "olpn": "T000010183",
            "type": "S",
            "units": 4,
            "case": 3,
            "location": "D1-SN-01",
            "loc_type": "PACKING",
            "created": "22:39",
            "timer_min": 7,
            "severity": "green"
        },
        {
            "olpn": "T000008905",
            "type": "M",
            "units": 15,
            "case": 3,
            "location": "D1-PW-10",
            "loc_type": "PACKING",
            "created": "22:31",
            "timer_min": 6,
            "severity": "green"
        },
        {
            "olpn": "T000009673",
            "type": "S",
            "units": 3,
            "case": 3,
            "location": "C1-PM-01",
            "loc_type": "PACKING",
            "created": "23:01",
            "timer_min": 6,
            "severity": "green"
        },
        {
            "olpn": "T000009805",
            "type": "S",
            "units": 23,
            "case": 3,
            "location": "D1-SN-01",
            "loc_type": "PACKING",
            "created": "22:17",
            "timer_min": 5,
            "severity": "green"
        }
    ],
    "putwalls": [
        {
            "pw": "PW1",
            "mawm_prefix": "S1-PW-010",
            "olpn_count": 0,
            "dz1": "D1-PW-01",
            "dz2": "D1-PW-09",
            "active_dz": null
        },
        {
            "pw": "PW2",
            "mawm_prefix": "S1-PW-020",
            "olpn_count": 27,
            "dz1": "D1-PW-02",
            "dz2": "D1-PW-10",
            "active_dz": "D1-PW-10"
        },
        {
            "pw": "PW3",
            "mawm_prefix": "S1-PW-030",
            "olpn_count": 0,
            "dz1": "D1-PW-03",
            "dz2": "D1-PW-11",
            "active_dz": null
        },
        {
            "pw": "PW4",
            "mawm_prefix": "S1-PW-040",
            "olpn_count": 1,
            "dz1": "D1-PW-04",
            "dz2": "D1-PW-12",
            "active_dz": null
        },
        {
            "pw": "PW5",
            "mawm_prefix": "S1-PW-050",
            "olpn_count": 0,
            "dz1": "D1-PW-05",
            "dz2": "D1-PW-13",
            "active_dz": null
        },
        {
            "pw": "PW6",
            "mawm_prefix": "S1-PW-060",
            "olpn_count": 1,
            "dz1": "D1-PW-06",
            "dz2": "D1-PW-14",
            "active_dz": null
        },
        {
            "pw": "PW7",
            "mawm_prefix": "S1-PW-070",
            "olpn_count": 0,
            "dz1": "D1-PW-07",
            "dz2": "D1-PW-15",
            "active_dz": null
        },
        {
            "pw": "PW8",
            "mawm_prefix": "S1-PW-080",
            "olpn_count": 1,
            "dz1": "D1-PW-08",
            "dz2": "D1-PW-16",
            "active_dz": null
        },
        {
            "pw": "H1",
            "mawm_prefix": "H1-PW-01",
            "olpn_count": 9,
            "dz1": "D1-HP-01",
            "dz2": null,
            "active_dz": null
        }
    ]
}